flavius_api/__init__.py
flavius_api/api.py
flavius_api/checks.py
flavius_api/conf.py
flavius_api-1.17.0.dist-info/LICENSE
flavius_api-1.17.0.dist-info/METADATA
flavius_api-1.17.0.dist-info/WHEEL
flavius_api-1.17.0.dist-info/top_level.txt
flavius_api-1.17.0.dist-info/RECORD
