Metadata-Version: 2.1
Name: flavius-api
Version: 1.17.0
Summary: FlaviusへAPI接続するためのパッケージ
Home-page: https://github.com/gnsjapan/flavuis_api
Author: Koichi Ezato
Author-email: ezato@gnsjapan.jp
Project-URL: Bug Tracker, https://github.com/gnsjapan/flavuis_api/issues
Classifier: Programming Language :: Python :: 3
Classifier: License :: Other/Proprietary License
Classifier: Operating System :: OS Independent
Requires-Python: >=3.6
License-File: LICENSE
Requires-Dist: requests
